{
  "title": "Bridal Special Mehndi in DHA Phase 1, Islamabad (Residence 21)",
  "metaTitle": "Bridal Special Mehndi DHA Phase 1 Islamabad | GlamUp at Residence 21",
  "metaDescription": "Custom bridal mehndi at Residence 21, DHA Phase 1, Islamabad. Intricate designs, rich stain, hygienic cones.",
  "keywords": ["bridal mehndi Islamabad", "henna DHA Phase 1", "Residence 21 mehndi", "wedding mehndi artist"],
  "intro": "Get intricate, symmetrical bridal mehndi with fresh, hygienic cones for a deep, lasting stain—applied at Residence 21.",
  "price": 6999,
  "originalPrice": 8500,
  "discount": 18,
  "duration": "120–180 minutes",
  "rating": 4.9,
  "reviews": 112,
  "city": "Islamabad",
  "area": "DHA Phase 1",
  "service": "Bridal Special Mehndi",
  "image": "/images/bridal-special-mehndi-islamabad-dha-phase1-residence-21.webp",
  "imageAlt": "Bridal mehndi at Residence 21 DHA Phase 1 Islamabad",
  "imageTitle": "Bridal Special Mehndi - Residence 21, DHA Phase 1 Islamabad",
  "imageCaption": "Bespoke motifs with a rich, natural stain.",
  "productCategorySlug": "mehndi-service",
  "features": [
    { "title": "Custom Patterns", "description": "Traditional to modern as per your taste." },
    { "title": "Fresh Cones", "description": "Prepared for strong, safe staining." },
    { "title": "Symmetry & Detail", "description": "Expert control for crisp lines." },
    { "title": "Comfortable Pacing", "description": "Breaks included to avoid fatigue." },
    { "title": "Aftercare", "description": "Maximize stain depth and longevity." },
    { "title": "On-Site Setup", "description": "We bring essentials to Residence 21." }
  ],
  "faq": [
    { "q": "Trial available?", "a": "Yes, trial motifs can be arranged." },
    { "q": "How long to keep paste?", "a": "6–8 hours for a deep stain." },
    { "q": "Any allergies?", "a": "Inform us if you have skin sensitivities." }
  ]
}
